keplar/__init__.py
keplar/client.py
keplar/core/__init__.py
keplar/core/api_error.py
keplar/core/client_wrapper.py
keplar/core/datetime_utils.py
keplar/core/file.py
keplar/core/force_multipart.py
keplar/core/http_client.py
keplar/core/http_response.py
keplar/core/jsonable_encoder.py
keplar/core/pydantic_utilities.py
keplar/core/query_encoder.py
keplar/core/remove_none_from_dict.py
keplar/core/request_options.py
keplar/core/serialization.py
keplar/environment.py
keplar/errors/__init__.py
keplar/errors/bad_request_error.py
keplar/errors/not_found_error.py
keplar/py.typed
keplar/raw_client.py
keplar/types/__init__.py
keplar/types/bad_request_error_body.py
keplar/types/bad_request_error_response.py
keplar/types/call.py
keplar/types/call_event.py
keplar/types/call_event_data.py
keplar/types/call_event_metadata.py
keplar/types/call_kind.py
keplar/types/call_metadata.py
keplar/types/call_status.py
keplar/types/chat_message.py
keplar/types/chat_message_kind.py
keplar/types/chat_message_metadata.py
keplar/types/chat_message_role.py
keplar/types/chat_session.py
keplar/types/citation.py
keplar/types/code_invite.py
keplar/types/code_invite_files_item.py
keplar/types/code_invite_project_config.py
keplar/types/code_invite_response.py
keplar/types/component.py
keplar/types/component_base.py
keplar/types/conversation_message.py
keplar/types/conversation_message_topic.py
keplar/types/create_chat_session_response.py
keplar/types/delete_chat_session_response.py
keplar/types/file.py
keplar/types/file_metadata.py
keplar/types/file_mime_type.py
keplar/types/forbidden_error_response.py
keplar/types/get_api_chats_response_item.py
keplar/types/get_api_chats_response_item_message_count.py
keplar/types/get_api_invites_id_responses_response.py
keplar/types/get_api_projects_project_id_files_response.py
keplar/types/get_api_projects_response.py
keplar/types/get_api_threads_response.py
keplar/types/get_api_threads_thread_id_files_response.py
keplar/types/get_chat_session_response.py
keplar_api_python-0.0.793.dist-info/METADATA
keplar_api_python-0.0.793.dist-info/WHEEL
keplar_api_python-0.0.793.dist-info/RECORD
